{"results": [{"results": [{"textDetection": {"pages": [{"blocks": [{"boundingBox": {"vertices": [{"x": "80", "y": "67"}, {"x": "80", "y": "104"}, {"x": "828", "y": "104"}, {"x": "828", "y": "67"}]}, "lines": [{"boundingBox": {"vertices": [{"x": "80", "y": "67"}, {"x": "80", "y": "104"}, {"x": "828", "y": "104"}, {"x": "828", "y": "67"}]}, "words": [{"boundingBox": {"vertices": [{"x": "80", "y": "71"}, {"x": "80", "y": "101"}, {"x": "103", "y": "101"}, {"x": "103", "y": "71"}]}, "languages": [{"languageCode": "en", "confidence": 0.8870053887}], "text": "\u00a9", "confidence": 0.8870053887, "entityIndex": "-1"}, {"boundingBox": {"vertices": [{"x": "119", "y": "71"}, {"x": "119", "y": "102"}, {"x": "206", "y": "102"}, {"x": "206", "y": "71"}]}, "languages": [{"languageCode": "en", "confidence": 0.8870053887}], "text": "E-T-A", "confidence": 0.8870053887, "entityIndex": "-1"}, {"boundingBox": {"vertices": [{"x": "233", "y": "72"}, {"x": "233", "y": "103"}, {"x": "383", "y": "103"}, {"x": "383", "y": "72"}]}, "languages": [{"languageCode": "en", "confidence": 0.8870053887}], "text": "3120-N\u2026", "confidence": 0.8870053887, "entityIndex": "-1"}, {"boundingBox": {"vertices": [{"x": "403", "y": "73"}, {"x": "403", "y": "104"}, {"x": "549", "y": "104"}, {"x": "549", "y": "73"}]}, "languages": [{"languageCode": "en", "confidence": 0.8870053887}], "text": "Thermal", "confidence": 0.8870053887, "entityIndex": "-1"}, {"boundingBox": {"vertices": [{"x": "566", "y": "74"}, {"x": "566", "y": "105"}, {"x": "687", "y": "105"}, {"x": "687", "y": "74"}]}, "languages": [{"languageCode": "en", "confidence": 0.8870053887}], "text": "Circuit", "confidence": 0.8870053887, "entityIndex": "-1"}, {"boundingBox": {"vertices": [{"x": "700", "y": "75"}, {"x": "700", "y": "106"}, {"x": "828", "y": "106"}, {"x": "828", "y": "75"}]}, "languages": [{"languageCode": "en", "confidence": 0.8870053887}], "text": "Breaker", "confidence": 0.8870053887, "entityIndex": "-1"}], "confidence": 0.8870053887}]}, {"boundingBox": {"vertices": [{"x": "91", "y": "167"}, {"x": "91", "y": "187"}, {"x": "433", "y": "187"}, {"x": "433", "y": "167"}]}, "lines": [{"boundingBox": {"vertices": [{"x": "91", "y": "167"}, {"x": "91", "y": "187"}, {"x": "433", "y": "187"}, {"x": "433", "y": "167"}]}, "words": [{"boundingBox": {"vertices": [{"x": "91", "y": "169"}, {"x": "91", "y": "188"}, {"x": "148", "y": "188"}, {"x": "148", "y": "169"}]}, "languages": [{"languageCode": "en", "confidence": 0.8971880078}], "text": "Cable", "confidence": 0.8971880078, "entityIndex": "-1"}, {"boundingBox": {"vertices": [{"x": "157", "y": "169"}, {"x": "157", "y": "188"}, {"x": "210", "y": "188"}, {"x": "210", "y": "169"}]}, "languages": [{"languageCode": "en", "confidence": 0.8971880078}], "text": "cross", "confidence": 0.8971880078, "entityIndex": "-1"}, {"boundingBox": {"vertices": [{"x": "218", "y": "168"}, {"x": "218", "y": "187"}, {"x": "300", "y": "187"}, {"x": "300", "y": "168"}]}, "languages": [{"languageCode": "en", "confidence": 0.8971880078}], "text": "sections", "confidence": 0.8971880078, "entityIndex": "-1"}, {"boundingBox": {"vertices": [{"x": "308", "y": "168"}, {"x": "308", "y": "187"}, {"x": "330", "y": "187"}, {"x": "330", "y": "168"}]}, "languages": [{"languageCode": "en", "confidence": 0.8971880078}], "text": "PT", "confidence": 0.8971880078, "entityIndex": "-1"}, {"boundingBox": {"vertices": [{"x": "339", "y": "168"}, {"x": "339", "y": "187"}, {"x": "433", "y": "187"}, {"x": "433", "y": "168"}]}, "languages": [{"languageCode": "en", "confidence": 0.8971880078}], "text": "terminals", "confidence": 0.8971880078, "entityIndex": "-1"}], "confidence": 0.8971880078}]}, {"boundingBox": {"vertices": [{"x": "634", "y": "164"}, {"x": "634", "y": "190"}, {"x": "784", "y": "190"}, {"x": "784", "y": "164"}]}, "lines": [{"boundingBox": {"vertices": [{"x": "634", "y": "164"}, {"x": "634", "y": "190"}, {"x": "784", "y": "190"}, {"x": "784", "y": "164"}]}, "words": [{"boundingBox": {"vertices": [{"x": "634", "y": "168"}, {"x": "634", "y": "188"}, {"x": "722", "y": "188"}, {"x": "722", "y": "168"}]}, "languages": [{"languageCode": "en", "confidence": 0.8791332245}], "text": "Terminal", "confidence": 0.8791332245, "entityIndex": "-1"}, {"boundingBox": {"vertices": [{"x": "729", "y": "168"}, {"x": "729", "y": "188"}, {"x": "784", "y": "188"}, {"x": "784", "y": "168"}]}, "languages": [{"languageCode": "en", "confidence": 0.8791332245}], "text": "types", "confidence": 0.8791332245, "entityIndex": "-1"}], "confidence": 0.8791332245}]}, {"boundingBox": {"vertices": [{"x": "86", "y": "218"}, {"x": "86", "y": "234"}, {"x": "132", "y": "234"}, {"x": "132", "y": "218"}]}, "lines": [{"boundingBox": {"vertices": [{"x": "86", "y": "218"}, {"x": "86", "y": "234"}, {"x": "132", "y": "234"}, {"x": "132", "y": "218"}]}, "words": [{"boundingBox": {"vertices": [{"x": "86", "y": "218"}, {"x": "86", "y": "233"}, {"x": "132", "y": "233"}, {"x": "132", "y": "218"}]}, "languages": [{"languageCode": "en", "confidence": 0.9449284673}], "text": "Cable", "confidence": 0.9449284673, "entityIndex": "-1"}], "confidence": 0.9449284673}]}, {"boundingBox": {"vertices": [{"x": "87", "y": "269"}, {"x": "87", "y": "284"}, {"x": "124", "y": "284"}, {"x": "124", "y": "269"}]}, "lines": [{"boundingBox": {"vertices": [{"x": "87", "y": "269"}, {"x": "87", "y": "284"}, {"x": "124", "y": "284"}, {"x": "124", "y": "269"}]}, "words": [{"boundingBox": {"vertices": [{"x": "87", "y": "269"}, {"x": "87", "y": "284"}, {"x": "124", "y": "284"}, {"x": "124", "y": "269"}]}, "languages": [{"languageCode": "en", "confidence": 0.8982613683}], "text": "Rigid", "confidence": 0.8982613683, "entityIndex": "-1"}], "confidence": 0.8982613683}]}, {"boundingBox": {"vertices": [{"x": "340", "y": "219"}, {"x": "340", "y": "306"}, {"x": "541", "y": "306"}, {"x": "541", "y": "219"}]}, "lines": [{"boundingBox": {"vertices": [{"x": "341", "y": "219"}, {"x": "341", "y": "233"}, {"x": "541", "y": "233"}, {"x": "541", "y": "219"}]}, "words": [{"boundingBox": {"vertices": [{"x": "341", "y": "219"}, {"x": "341", "y": "234"}, {"x": "386", "y": "234"}, {"x": "386", "y": "219"}]}, "languages": [{"languageCode": "en", "confidence": 0.8939578533}], "text": "cross", "confidence": 0.8939578533, "entityIndex": "-1"}, {"boundingBox": {"vertices": [{"x": "393", "y": "219"}, {"x": "393", "y": "233"}, {"x": "448", "y": "233"}, {"x": "448", "y": "219"}]}, "languages": [{"languageCode": "en", "confidence": 0.8939578533}], "text": "section", "confidence": 0.8939578533, "entityIndex": "-1"}, {"boundingBox": {"vertices": [{"x": "456", "y": "219"}, {"x": "456", "y": "233"}, {"x": "487", "y": "233"}, {"x": "487", "y": "219"}]}, "languages": [{"languageCode": "en", "confidence": 0.8939578533}], "text": "with", "confidence": 0.8939578533, "entityIndex": "-1"}, {"boundingBox": {"vertices": [{"x": "495", "y": "219"}, {"x": "495", "y": "233"}, {"x": "541", "y": "233"}, {"x": "541", "y": "219"}]}, "languages": [{"languageCode": "en", "confidence": 0.8939578533}], "text": "direct", "confidence": 0.8939578533, "entityIndex": "-1"}], "confidence": 0.8939578533}, {"boundingBox": {"vertices": [{"x": "342", "y": "240"}, {"x": "342", "y": "256"}, {"x": "456", "y": "256"}, {"x": "456", "y": "240"}]}, "words": [{"boundingBox": {"vertices": [{"x": "342", "y": "240"}, {"x": "342", "y": "255"}, {"x": "402", "y": "255"}, {"x": "402", "y": "240"}]}, "languages": [{"languageCode": "en", "confidence": 0.9070305824}], "text": "push-in", "confidence": 0.9070305824, "entityIndex": "-1"}, {"boundingBox": {"vertices": [{"x": "409", "y": "240"}, {"x": "409", "y": "255"}, {"x": "456", "y": "255"}, {"x": "456", "y": "240"}]}, "languages": [{"languageCode": "en", "confidence": 0.9070305824}], "text": "wiring", "confidence": 0.9070305824, "entityIndex": "-1"}], "confidence": 0.9070305824}, {"boundingBox": {"vertices": [{"x": "343", "y": "268"}, {"x": "343", "y": "284"}, {"x": "415", "y": "284"}, {"x": "415", "y": "268"}]}, "words": [{"boundingBox": {"vertices": [{"x": "343", "y": "271"}, {"x": "343", "y": "285"}, {"x": "376", "y": "285"}, {"x": "376", "y": "271"}]}, "languages": [{"languageCode": "en", "confidence": 0.8618466258}], "text": "1\u20264", "confidence": 0.8618466258, "entityIndex": "-1"}, {"boundingBox": {"vertices": [{"x": "383", "y": "269"}, {"x": "383", "y": "284"}, {"x": "415", "y": "284"}, {"x": "415", "y": "269"}]}, "languages": [{"languageCode": "en", "confidence": 0.8618466258}], "text": "mm2", "confidence": 0.8618466258, "entityIndex": "-1"}], "confidence": 0.8618466258}, {"boundingBox": {"vertices": [{"x": "340", "y": "290"}, {"x": "340", "y": "306"}, {"x": "532", "y": "306"}, {"x": "532", "y": "290"}]}, "words": [{"boundingBox": {"vertices": [{"x": "340", "y": "291"}, {"x": "340", "y": "306"}, {"x": "410", "y": "306"}, {"x": "410", "y": "291"}]}, "languages": [{"languageCode": "en", "confidence": 0.8543227911}], "text": "(stripping", "confidence": 0.8543227911, "entityIndex": "-1"}, {"boundingBox": {"vertices": [{"x": "414", "y": "291"}, {"x": "414", "y": "306"}, {"x": "468", "y": "306"}, {"x": "468", "y": "291"}]}, "languages": [{"languageCode": "en", "confidence": 0.8543227911}], "text": "length:", "confidence": 0.8543227911, "entityIndex": "-1"}, {"boundingBox": {"vertices": [{"x": "475", "y": "291"}, {"x": "475", "y": "306"}, {"x": "489", "y": "306"}, {"x": "489", "y": "291"}]}, "languages": [{"languageCode": "en", "confidence": 0.8543227911}], "text": "10", "confidence": 0.8543227911, "entityIndex": "-1"}, {"boundingBox": {"vertices": [{"x": "496", "y": "291"}, {"x": "496", "y": "306"}, {"x": "532", "y": "306"}, {"x": "532", "y": "291"}]}, "languages": [{"languageCode": "en", "confidence": 0.8543227911}], "text": "mm)", "confidence": 0.8543227911, "entityIndex": "-1"}], "confidence": 0.8543227911}]}, {"boundingBox": {"vertices": [{"x": "644", "y": "236"}, {"x": "644", "y": "275"}, {"x": "812", "y": "275"}, {"x": "812", "y": "236"}]}, "lines": [{"boundingBox": {"vertices": [{"x": "646", "y": "236"}, {"x": "646", "y": "254"}, {"x": "812", "y": "254"}, {"x": "812", "y": "236"}]}, "words": [{"boundingBox": {"vertices": [{"x": "646", "y": "238"}, {"x": "646", "y": "254"}, {"x": "699", "y": "254"}, {"x": "699", "y": "238"}]}, "languages": [{"languageCode": "en", "confidence": 0.932657063}], "text": "2-pole", "confidence": 0.932657063, "entityIndex": "-1"}, {"boundingBox": {"vertices": [{"x": "778", "y": "238"}, {"x": "778", "y": "254"}, {"x": "812", "y": "254"}, {"x": "812", "y": "238"}]}, "languages": [{"languageCode": "en", "confidence": 0.932657063}], "text": "and", "confidence": 0.932657063, "entityIndex": "-1"}], "confidence": 0.932657063}, {"boundingBox": {"vertices": [{"x": "644", "y": "258"}, {"x": "644", "y": "275"}, {"x": "776", "y": "275"}, {"x": "776", "y": "258"}]}, "words": [{"boundingBox": {"vertices": [{"x": "644", "y": "259"}, {"x": "644", "y": "274"}, {"x": "695", "y": "274"}, {"x": "695", "y": "259"}]}, "languages": [{"languageCode": "en", "confidence": 0.8915371895}], "text": "2-pole", "confidence": 0.8915371895, "entityIndex": "-1"}, {"boundingBox": {"vertices": [{"x": "702", "y": "258"}, {"x": "702", "y": "274"}, {"x": "776", "y": "274"}, {"x": "776", "y": "258"}]}, "languages": [{"languageCode": "en", "confidence": 0.8915371895}], "text": "protected", "confidence": 0.8915371895, "entityIndex": "-1"}], "confidence": 0.8915371895}]}, {"boundingBox": {"vertices": [{"x": "671", "y": "292"}, {"x": "671", "y": "309"}, {"x": "791", "y": "309"}, {"x": "791", "y": "292"}]}, "lines": [{"boundingBox": {"vertices": [{"x": "671", "y": "292"}, {"x": "671", "y": "309"}, {"x": "791", "y": "309"}, {"x": "791", "y": "292"}]}, "words": [{"boundingBox": {"vertices": [{"x": "671", "y": "292"}, {"x": "671", "y": "309"}, {"x": "791", "y": "309"}, {"x": "791", "y": "292"}]}, "languages": [{"languageCode": "en", "confidence": 0.9895743728}], "text": "3120-N524-PT", "confidence": 0.9895743728, "entityIndex": "-1"}], "confidence": 0.9895743728}]}, {"boundingBox": {"vertices": [{"x": "888", "y": "236"}, {"x": "888", "y": "275"}, {"x": "1061", "y": "275"}, {"x": "1061", "y": "236"}]}, "lines": [{"boundingBox": {"vertices": [{"x": "892", "y": "236"}, {"x": "892", "y": "255"}, {"x": "1061", "y": "255"}, {"x": "1061", "y": "236"}]}, "words": [{"boundingBox": {"vertices": [{"x": "892", "y": "238"}, {"x": "892", "y": "253"}, {"x": "943", "y": "253"}, {"x": "943", "y": "238"}]}, "languages": [{"languageCode": "en", "confidence": 0.9361155629}], "text": "2-pole", "confidence": 0.9361155629, "entityIndex": "-1"}, {"boundingBox": {"vertices": [{"x": "950", "y": "238"}, {"x": "950", "y": "254"}, {"x": "1024", "y": "254"}, {"x": "1024", "y": "238"}]}, "languages": [{"languageCode": "en", "confidence": 0.9361155629}], "text": "switching", "confidence": 0.9361155629, "entityIndex": "-1"}, {"boundingBox": {"vertices": [{"x": "1032", "y": "238"}, {"x": "1032", "y": "254"}, {"x": "1061", "y": "254"}, {"x": "1061", "y": "238"}]}, "languages": [{"languageCode": "en", "confidence": 0.9361155629}], "text": "and", "confidence": 0.9361155629, "entityIndex": "-1"}], "confidence": 0.9361155629}, {"boundingBox": {"vertices": [{"x": "888", "y": "258"}, {"x": "888", "y": "275"}, {"x": "1023", "y": "275"}, {"x": "1023", "y": "258"}]}, "words": [{"boundingBox": {"vertices": [{"x": "888", "y": "258"}, {"x": "888", "y": "274"}, {"x": "945", "y": "274"}, {"x": "945", "y": "258"}]}, "languages": [{"languageCode": "en", "confidence": 0.9341799617}], "text": "1-pole", "confidence": 0.9341799617, "entityIndex": "-1"}, {"boundingBox": {"vertices": [{"x": "953", "y": "258"}, {"x": "953", "y": "274"}, {"x": "1023", "y": "274"}, {"x": "1023", "y": "258"}]}, "languages": [{"languageCode": "en", "confidence": 0.9341799617}], "text": "protected", "confidence": 0.9341799617, "entityIndex": "-1"}], "confidence": 0.9341799617}]}, {"boundingBox": {"vertices": [{"x": "921", "y": "293"}, {"x": "921", "y": "308"}, {"x": "1033", "y": "308"}, {"x": "1033", "y": "293"}]}, "lines": [{"boundingBox": {"vertices": [{"x": "921", "y": "293"}, {"x": "921", "y": "308"}, {"x": "1033", "y": "308"}, {"x": "1033", "y": "293"}]}, "words": [{"boundingBox": {"vertices": [{"x": "921", "y": "293"}, {"x": "921", "y": "309"}, {"x": "1033", "y": "309"}, {"x": "1033", "y": "293"}]}, "languages": [{"languageCode": "en", "confidence": 0.9918848872}], "text": "3120-N554-PT", "confidence": 0.9918848872, "entityIndex": "-1"}], "confidence": 0.9918848872}]}, {"boundingBox": {"vertices": [{"x": "83", "y": "319"}, {"x": "83", "y": "356"}, {"x": "315", "y": "356"}, {"x": "315", "y": "319"}]}, "lines": [{"boundingBox": {"vertices": [{"x": "84", "y": "319"}, {"x": "84", "y": "336"}, {"x": "300", "y": "336"}, {"x": "300", "y": "319"}]}, "words": [{"boundingBox": {"vertices": [{"x": "84", "y": "321"}, {"x": "84", "y": "335"}, {"x": "143", "y": "335"}, {"x": "143", "y": "321"}]}, "languages": [{"languageCode": "en", "confidence": 0.9247246981}], "text": "Flexible", "confidence": 0.9247246981, "entityIndex": "-1"}, {"boundingBox": {"vertices": [{"x": "151", "y": "321"}, {"x": "151", "y": "335"}, {"x": "177", "y": "335"}, {"x": "177", "y": "321"}]}, "languages": [{"languageCode": "en", "confidence": 0.9247246981}], "text": "with", "confidence": 0.9247246981, "entityIndex": "-1"}, {"boundingBox": {"vertices": [{"x": "186", "y": "321"}, {"x": "186", "y": "335"}, {"x": "214", "y": "335"}, {"x": "214", "y": "321"}]}, "languages": [{"languageCode": "en", "confidence": 0.9247246981}], "text": "wire", "confidence": 0.9247246981, "entityIndex": "-1"}, {"boundingBox": {"vertices": [{"x": "221", "y": "321"}, {"x": "221", "y": "336"}, {"x": "247", "y": "336"}, {"x": "247", "y": "321"}]}, "languages": [{"languageCode": "en", "confidence": 0.9247246981}], "text": "end", "confidence": 0.9247246981, "entityIndex": "-1"}, {"boundingBox": {"vertices": [{"x": "254", "y": "321"}, {"x": "254", "y": "336"}, {"x": "300", "y": "336"}, {"x": "300", "y": "321"}]}, "languages": [{"languageCode": "en", "confidence": 0.9247246981}], "text": "ferrule", "confidence": 0.9247246981, "entityIndex": "-1"}], "confidence": 0.9247246981}, {"boundingBox": {"vertices": [{"x": "83", "y": "341"}, {"x": "83", "y": "356"}, {"x": "315", "y": "356"}, {"x": "315", "y": "341"}]}, "words": [{"boundingBox": {"vertices": [{"x": "83", "y": "341"}, {"x": "83", "y": "356"}, {"x": "120", "y": "356"}, {"x": "120", "y": "341"}]}, "languages": [{"languageCode": "en", "confidence": 0.8444962502}], "text": "(with", "confidence": 0.8444962502, "entityIndex": "-1"}, {"boundingBox": {"vertices": [{"x": "128", "y": "342"}, {"x": "128", "y": "356"}, {"x": "141", "y": "356"}, {"x": "141", "y": "342"}]}, "languages": [{"languageCode": "en", "confidence": 0.8444962502}], "text": "or", "confidence": 0.8444962502, "entityIndex": "-1"}, {"boundingBox": {"vertices": [{"x": "148", "y": "342"}, {"x": "148", "y": "356"}, {"x": "203", "y": "356"}, {"x": "203", "y": "342"}]}, "languages": [{"languageCode": "en", "confidence": 0.8444962502}], "text": "without", "confidence": 0.8444962502, "entityIndex": "-1"}, {"boundingBox": {"vertices": [{"x": "209", "y": "342"}, {"x": "209", "y": "356"}, {"x": "254", "y": "356"}, {"x": "254", "y": "342"}]}, "languages": [{"languageCode": "en", "confidence": 0.8444962502}], "text": "plastic", "confidence": 0.8444962502, "entityIndex": "-1"}, {"boundingBox": {"vertices": [{"x": "261", "y": "342"}, {"x": "261", "y": "356"}, {"x": "315", "y": "356"}, {"x": "315", "y": "342"}]}, "languages": [{"languageCode": "en", "confidence": 0.8444962502}], "text": "sleeve)", "confidence": 0.8444962502, "entityIndex": "-1"}], "confidence": 0.8444962502}]}, {"boundingBox": {"vertices": [{"x": "343", "y": "319"}, {"x": "343", "y": "335"}, {"x": "444", "y": "335"}, {"x": "444", "y": "319"}]}, "lines": [{"boundingBox": {"vertices": [{"x": "343", "y": "319"}, {"x": "343", "y": "335"}, {"x": "444", "y": "335"}, {"x": "444", "y": "319"}]}, "words": [{"boundingBox": {"vertices": [{"x": "343", "y": "320"}, {"x": "343", "y": "335"}, {"x": "401", "y": "335"}, {"x": "401", "y": "320"}]}, "languages": [{"languageCode": "en", "confidence": 0.9227575064}], "text": "0.5\u20262.5", "confidence": 0.9227575064, "entityIndex": "-1"}, {"boundingBox": {"vertices": [{"x": "408", "y": "320"}, {"x": "408", "y": "335"}, {"x": "444", "y": "335"}, {"x": "444", "y": "320"}]}, "languages": [{"languageCode": "en", "confidence": 0.9227575064}], "text": "mm2", "confidence": 0.9227575064, "entityIndex": "-1"}], "confidence": 0.9227575064}]}, {"boundingBox": {"vertices": [{"x": "86", "y": "370"}, {"x": "86", "y": "386"}, {"x": "132", "y": "386"}, {"x": "132", "y": "370"}]}, "lines": [{"boundingBox": {"vertices": [{"x": "86", "y": "370"}, {"x": "86", "y": "386"}, {"x": "132", "y": "386"}, {"x": "132", "y": "370"}]}, "words": [{"boundingBox": {"vertices": [{"x": "86", "y": "370"}, {"x": "86", "y": "385"}, {"x": "132", "y": "385"}, {"x": "132", "y": "370"}]}, "languages": [{"languageCode": "en", "confidence": 0.929389298}], "text": "Cable", "confidence": 0.929389298, "entityIndex": "-1"}], "confidence": 0.929389298}]}, {"boundingBox": {"vertices": [{"x": "339", "y": "371"}, {"x": "339", "y": "407"}, {"x": "566", "y": "407"}, {"x": "566", "y": "371"}]}, "lines": [{"boundingBox": {"vertices": [{"x": "341", "y": "371"}, {"x": "341", "y": "387"}, {"x": "566", "y": "387"}, {"x": "566", "y": "371"}]}, "words": [{"boundingBox": {"vertices": [{"x": "341", "y": "371"}, {"x": "341", "y": "385"}, {"x": "386", "y": "385"}, {"x": "386", "y": "371"}]}, "languages": [{"languageCode": "en", "confidence": 0.8944095373}], "text": "cross", "confidence": 0.8944095373, "entityIndex": "-1"}, {"boundingBox": {"vertices": [{"x": "393", "y": "371"}, {"x": "393", "y": "385"}, {"x": "448", "y": "385"}, {"x": "448", "y": "371"}]}, "languages": [{"languageCode": "en", "confidence": 0.8944095373}], "text": "section", "confidence": 0.8944095373, "entityIndex": "-1"}, {"boundingBox": {"vertices": [{"x": "456", "y": "371"}, {"x": "456", "y": "386"}, {"x": "495", "y": "386"}, {"x": "495", "y": "371"}]}, "languages": [{"languageCode": "en", "confidence": 0.8944095373}], "text": "when", "confidence": 0.8944095373, "entityIndex": "-1"}, {"boundingBox": {"vertices": [{"x": "504", "y": "372"}, {"x": "504", "y": "386"}, {"x": "566", "y": "386"}, {"x": "566", "y": "372"}]}, "languages": [{"languageCode": "en", "confidence": 0.8944095373}], "text": "opening", "confidence": 0.8944095373, "entityIndex": "-1"}], "confidence": 0.8944095373}, {"boundingBox": {"vertices": [{"x": "339", "y": "392"}, {"x": "339", "y": "407"}, {"x": "513", "y": "407"}, {"x": "513", "y": "392"}]}, "words": [{"boundingBox": {"vertices": [{"x": "339", "y": "392"}, {"x": "339", "y": "407"}, {"x": "366", "y": "407"}, {"x": "366", "y": "392"}]}, "languages": [{"languageCode": "en", "confidence": 0.8960830569}], "text": "the", "confidence": 0.8960830569, "entityIndex": "-1"}, {"boundingBox": {"vertices": [{"x": "374", "y": "392"}, {"x": "374", "y": "407"}, {"x": "431", "y": "407"}, {"x": "431", "y": "392"}]}, "languages": [{"languageCode": "en", "confidence": 0.8960830569}], "text": "push-in", "confidence": 0.8960830569, "entityIndex": "-1"}, {"boundingBox": {"vertices": [{"x": "438", "y": "392"}, {"x": "438", "y": "406"}, {"x": "513", "y": "406"}, {"x": "513", "y": "392"}]}, "languages": [{"languageCode": "en", "confidence": 0.8960830569}], "text": "terminals", "confidence": 0.8960830569, "entityIndex": "-1"}], "confidence": 0.8960830569}]}, {"boundingBox": {"vertices": [{"x": "84", "y": "421"}, {"x": "84", "y": "437"}, {"x": "127", "y": "437"}, {"x": "127", "y": "421"}]}, "lines": [{"boundingBox": {"vertices": [{"x": "84", "y": "421"}, {"x": "84", "y": "437"}, {"x": "127", "y": "437"}, {"x": "127", "y": "421"}]}, "words": [{"boundingBox": {"vertices": [{"x": "84", "y": "420"}, {"x": "84", "y": "437"}, {"x": "127", "y": "437"}, {"x": "127", "y": "420"}]}, "languages": [{"languageCode": "en", "confidence": 0.9451832175}], "text": "Rigid", "confidence": 0.9451832175, "entityIndex": "-1"}], "confidence": 0.9451832175}]}, {"boundingBox": {"vertices": [{"x": "339", "y": "420"}, {"x": "339", "y": "458"}, {"x": "530", "y": "458"}, {"x": "530", "y": "420"}]}, "lines": [{"boundingBox": {"vertices": [{"x": "343", "y": "420"}, {"x": "343", "y": "437"}, {"x": "434", "y": "437"}, {"x": "434", "y": "420"}]}, "words": [{"boundingBox": {"vertices": [{"x": "343", "y": "423"}, {"x": "343", "y": "437"}, {"x": "390", "y": "437"}, {"x": "390", "y": "423"}]}, "languages": [{"languageCode": "en", "confidence": 0.8421382904}], "text": "0.5\u20264", "confidence": 0.8421382904, "entityIndex": "-1"}, {"boundingBox": {"vertices": [{"x": "397", "y": "422"}, {"x": "397", "y": "436"}, {"x": "434", "y": "436"}, {"x": "434", "y": "422"}]}, "languages": [{"languageCode": "en", "confidence": 0.8421382904}], "text": "mm2", "confidence": 0.8421382904, "entityIndex": "-1"}], "confidence": 0.8421382904}, {"boundingBox": {"vertices": [{"x": "339", "y": "442"}, {"x": "339", "y": "458"}, {"x": "530", "y": "458"}, {"x": "530", "y": "442"}]}, "words": [{"boundingBox": {"vertices": [{"x": "339", "y": "443"}, {"x": "339", "y": "458"}, {"x": "409", "y": "458"}, {"x": "409", "y": "443"}]}, "languages": [{"languageCode": "en", "confidence": 0.8604877591}], "text": "(stripping", "confidence": 0.8604877591, "entityIndex": "-1"}, {"boundingBox": {"vertices": [{"x": "415", "y": "443"}, {"x": "415", "y": "458"}, {"x": "469", "y": "458"}, {"x": "469", "y": "443"}]}, "languages": [{"languageCode": "en", "confidence": 0.8604877591}], "text": "length:", "confidence": 0.8604877591, "entityIndex": "-1"}, {"boundingBox": {"vertices": [{"x": "474", "y": "443"}, {"x": "474", "y": "458"}, {"x": "488", "y": "458"}, {"x": "488", "y": "443"}]}, "languages": [{"languageCode": "en", "confidence": 0.8604877591}], "text": "10", "confidence": 0.8604877591, "entityIndex": "-1"}, {"boundingBox": {"vertices": [{"x": "497", "y": "443"}, {"x": "497", "y": "458"}, {"x": "530", "y": "458"}, {"x": "530", "y": "443"}]}, "languages": [{"languageCode": "en", "confidence": 0.8604877591}], "text": "mm)", "confidence": 0.8604877591, "entityIndex": "-1"}], "confidence": 0.8604877591}]}, {"boundingBox": {"vertices": [{"x": "84", "y": "470"}, {"x": "84", "y": "487"}, {"x": "446", "y": "487"}, {"x": "446", "y": "470"}]}, "lines": [{"boundingBox": {"vertices": [{"x": "84", "y": "470"}, {"x": "84", "y": "487"}, {"x": "446", "y": "487"}, {"x": "446", "y": "470"}]}, "words": [{"boundingBox": {"vertices": [{"x": "84", "y": "472"}, {"x": "84", "y": "486"}, {"x": "143", "y": "486"}, {"x": "143", "y": "472"}]}, "languages": [{"languageCode": "en", "confidence": 0.9640073776}], "text": "Flexible", "confidence": 0.9640073776, "entityIndex": "-1"}, {"boundingBox": {"vertices": [{"x": "150", "y": "472"}, {"x": "150", "y": "486"}, {"x": "203", "y": "486"}, {"x": "203", "y": "472"}]}, "languages": [{"languageCode": "en", "confidence": 0.9640073776}], "text": "without", "confidence": 0.9640073776, "entityIndex": "-1"}, {"boundingBox": {"vertices": [{"x": "207", "y": "472"}, {"x": "207", "y": "486"}, {"x": "237", "y": "486"}, {"x": "237", "y": "472"}]}, "languages": [{"languageCode": "en", "confidence": 0.9640073776}], "text": "wire", "confidence": 0.9640073776, "entityIndex": "-1"}, {"boundingBox": {"vertices": [{"x": "244", "y": "471"}, {"x": "244", "y": "486"}, {"x": "268", "y": "486"}, {"x": "268", "y": "471"}]}, "languages": [{"languageCode": "en", "confidence": 0.9640073776}], "text": "end", "confidence": 0.9640073776, "entityIndex": "-1"}, {"boundingBox": {"vertices": [{"x": "275", "y": "471"}, {"x": "275", "y": "486"}, {"x": "329", "y": "486"}, {"x": "329", "y": "471"}]}, "languages": [{"languageCode": "en", "confidence": 0.9640073776}], "text": "ferrule", "confidence": 0.9640073776, "entityIndex": "-1"}, {"boundingBox": {"vertices": [{"x": "342", "y": "471"}, {"x": "342", "y": "486"}, {"x": "402", "y": "486"}, {"x": "402", "y": "471"}]}, "languages": [{"languageCode": "en", "confidence": 0.9640073776}], "text": "0.5\u20262.5", "confidence": 0.9640073776, "entityIndex": "-1"}, {"boundingBox": {"vertices": [{"x": "410", "y": "471"}, {"x": "410", "y": "486"}, {"x": "446", "y": "486"}, {"x": "446", "y": "471"}]}, "languages": [{"languageCode": "en", "confidence": 0.9640073776}], "text": "mm2", "confidence": 0.9640073776, "entityIndex": "-1"}], "confidence": 0.9640073776}]}, {"boundingBox": {"vertices": [{"x": "87", "y": "523"}, {"x": "87", "y": "544"}, {"x": "285", "y": "544"}, {"x": "285", "y": "523"}]}, "lines": [{"boundingBox": {"vertices": [{"x": "87", "y": "523"}, {"x": "87", "y": "544"}, {"x": "285", "y": "544"}, {"x": "285", "y": "523"}]}, "words": [{"boundingBox": {"vertices": [{"x": "87", "y": "523"}, {"x": "87", "y": "542"}, {"x": "198", "y": "542"}, {"x": "198", "y": "523"}]}, "languages": [{"languageCode": "en", "confidence": 0.914398551}], "text": "Installation", "confidence": 0.914398551, "entityIndex": "-1"}, {"boundingBox": {"vertices": [{"x": "208", "y": "524"}, {"x": "208", "y": "543"}, {"x": "285", "y": "543"}, {"x": "285", "y": "524"}]}, "languages": [{"languageCode": "en", "confidence": 0.914398551}], "text": "drawing", "confidence": 0.914398551, "entityIndex": "-1"}], "confidence": 0.914398551}]}, {"boundingBox": {"vertices": [{"x": "674", "y": "529"}, {"x": "674", "y": "545"}, {"x": "788", "y": "545"}, {"x": "788", "y": "529"}]}, "lines": [{"boundingBox": {"vertices": [{"x": "674", "y": "529"}, {"x": "674", "y": "545"}, {"x": "788", "y": "545"}, {"x": "788", "y": "529"}]}, "words": [{"boundingBox": {"vertices": [{"x": "674", "y": "529"}, {"x": "674", "y": "545"}, {"x": "788", "y": "545"}, {"x": "788", "y": "529"}]}, "languages": [{"languageCode": "en", "confidence": 0.9473176003}], "text": "3120-N524-P7", "confidence": 0.9473176003, "entityIndex": "-1"}], "confidence": 0.9473176003}]}, {"boundingBox": {"vertices": [{"x": "918", "y": "529"}, {"x": "918", "y": "546"}, {"x": "1038", "y": "546"}, {"x": "1038", "y": "529"}]}, "lines": [{"boundingBox": {"vertices": [{"x": "918", "y": "529"}, {"x": "918", "y": "546"}, {"x": "1038", "y": "546"}, {"x": "1038", "y": "529"}]}, "words": [{"boundingBox": {"vertices": [{"x": "918", "y": "529"}, {"x": "918", "y": "545"}, {"x": "1038", "y": "545"}, {"x": "1038", "y": "529"}]}, "languages": [{"languageCode": "en", "confidence": 0.9528561234}], "text": "3120-N554-P7", "confidence": 0.9528561234, "entityIndex": "-1"}], "confidence": 0.9528561234}]}, {"boundingBox": {"vertices": [{"x": "126", "y": "586"}, {"x": "126", "y": "602"}, {"x": "331", "y": "602"}, {"x": "331", "y": "586"}]}, "lines": [{"boundingBox": {"vertices": [{"x": "126", "y": "586"}, {"x": "126", "y": "602"}, {"x": "331", "y": "602"}, {"x": "331", "y": "586"}]}, "words": [{"boundingBox": {"vertices": [{"x": "126", "y": "587"}, {"x": "126", "y": "601"}, {"x": "163", "y": "601"}, {"x": "163", "y": "587"}]}, "languages": [{"languageCode": "en", "confidence": 0.9059780836}], "text": "3120", "confidence": 0.9059780836, "entityIndex": "-1"}, {"boundingBox": {"vertices": [{"x": "170", "y": "587"}, {"x": "170", "y": "602"}, {"x": "205", "y": "602"}, {"x": "205", "y": "587"}]}, "languages": [{"languageCode": "en", "confidence": 0.9059780836}], "text": "with", "confidence": 0.9059780836, "entityIndex": "-1"}, {"boundingBox": {"vertices": [{"x": "212", "y": "587"}, {"x": "212", "y": "602"}, {"x": "252", "y": "602"}, {"x": "252", "y": "587"}]}, "languages": [{"languageCode": "en", "confidence": 0.9059780836}], "text": "blade", "confidence": 0.9059780836, "entityIndex": "-1"}, {"boundingBox": {"vertices": [{"x": "256", "y": "588"}, {"x": "256", "y": "603"}, {"x": "331", "y": "603"}, {"x": "331", "y": "588"}]}, "languages": [{"languageCode": "en", "confidence": 0.9059780836}], "text": "terminals", "confidence": 0.9059780836, "entityIndex": "-1"}], "confidence": 0.9059780836}]}, {"boundingBox": {"vertices": [{"x": "333", "y": "615"}, {"x": "333", "y": "647"}, {"x": "523", "y": "647"}, {"x": "523", "y": "615"}]}, "lines": [{"boundingBox": {"vertices": [{"x": "334", "y": "615"}, {"x": "334", "y": "630"}, {"x": "523", "y": "630"}, {"x": "523", "y": "615"}]}, "words": [{"boundingBox": {"vertices": [{"x": "334", "y": "618"}, {"x": "334", "y": "628"}, {"x": "361", "y": "628"}, {"x": "361", "y": "618"}]}, "languages": [{"languageCode": "en", "confidence": 0.962523818}], "text": "When", "confidence": 0.962523818, "entityIndex": "-1"}, {"boundingBox": {"vertices": [{"x": "366", "y": "618"}, {"x": "366", "y": "628"}, {"x": "415", "y": "628"}, {"x": "415", "y": "618"}]}, "languages": [{"languageCode": "en", "confidence": 0.962523818}], "text": "Installing", "confidence": 0.962523818, "entityIndex": "-1"}, {"boundingBox": {"vertices": [{"x": "420", "y": "618"}, {"x": "420", "y": "628"}, {"x": "443", "y": "628"}, {"x": "443", "y": "618"}]}, "languages": [{"languageCode": "en", "confidence": 0.962523818}], "text": "the", "confidence": 0.962523818, "entityIndex": "-1"}, {"boundingBox": {"vertices": [{"x": "475", "y": "618"}, {"x": "475", "y": "628"}, {"x": "523", "y": "628"}, {"x": "523", "y": "618"}]}, "languages": [{"languageCode": "en", "confidence": 0.962523818}], "text": "breaker", "confidence": 0.962523818, "entityIndex": "-1"}], "confidence": 0.962523818}, {"boundingBox": {"vertices": [{"x": "333", "y": "632"}, {"x": "333", "y": "647"}, {"x": "497", "y": "647"}, {"x": "497", "y": "632"}]}, "words": [{"boundingBox": {"vertices": [{"x": "333", "y": "633"}, {"x": "333", "y": "646"}, {"x": "362", "y": "646"}, {"x": "362", "y": "633"}]}, "languages": [{"languageCode": "en", "confidence": 0.8878394961}], "text": "apply", "confidence": 0.8878394961, "entityIndex": "-1"}, {"boundingBox": {"vertices": [{"x": "368", "y": "632"}, {"x": "368", "y": "645"}, {"x": "414", "y": "645"}, {"x": "414", "y": "632"}]}, "languages": [{"languageCode": "en", "confidence": 0.8878394961}], "text": "pressure", "confidence": 0.8878394961, "entityIndex": "-1"}, {"boundingBox": {"vertices": [{"x": "419", "y": "632"}, {"x": "419", "y": "645"}, {"x": "429", "y": "645"}, {"x": "429", "y": "632"}]}, "languages": [{"languageCode": "en", "confidence": 0.8878394961}], "text": "on", "confidence": 0.8878394961, "entityIndex": "-1"}, {"boundingBox": {"vertices": [{"x": "435", "y": "633"}, {"x": "435", "y": "645"}, {"x": "466", "y": "645"}, {"x": "466", "y": "633"}]}, "languages": [{"languageCode": "en", "confidence": 0.8878394961}], "text": "bezel", "confidence": 0.8878394961, "entityIndex": "-1"}, {"boundingBox": {"vertices": [{"x": "470", "y": "633"}, {"x": "470", "y": "645"}, {"x": "497", "y": "645"}, {"x": "497", "y": "633"}]}, "languages": [{"languageCode": "en", "confidence": 0.8878394961}], "text": "only.", "confidence": 0.8878394961, "entityIndex": "-1"}], "confidence": 0.8878394961}]}, {"boundingBox": {"vertices": [{"x": "240", "y": "668"}, {"x": "240", "y": "680"}, {"x": "321", "y": "680"}, {"x": "321", "y": "668"}]}, "lines": [{"boundingBox": {"vertices": [{"x": "240", "y": "668"}, {"x": "240", "y": "680"}, {"x": "321", "y": "680"}, {"x": "321", "y": "668"}]}, "words": [{"boundingBox": {"vertices": [{"x": "240", "y": "668"}, {"x": "240", "y": "680"}, {"x": "292", "y": "680"}, {"x": "292", "y": "668"}]}, "languages": [{"languageCode": "en", "confidence": 0.8356184959}], "text": "operating", "confidence": 0.8356184959, "entityIndex": "-1"}, {"boundingBox": {"vertices": [{"x": "298", "y": "668"}, {"x": "298", "y": "679"}, {"x": "321", "y": "679"}, {"x": "321", "y": "668"}]}, "languages": [{"languageCode": "en", "confidence": 0.8356184959}], "text": "area", "confidence": 0.8356184959, "entityIndex": "-1"}], "confidence": 0.8356184959}]}, {"boundingBox": {"vertices": [{"x": "542", "y": "786"}, {"x": "542", "y": "796"}, {"x": "553", "y": "796"}, {"x": "553", "y": "786"}]}, "lines": [{"boundingBox": {"vertices": [{"x": "542", "y": "786"}, {"x": "542", "y": "796"}, {"x": "553", "y": "796"}, {"x": "553", "y": "786"}]}, "words": [{"boundingBox": {"vertices": [{"x": "542", "y": "786"}, {"x": "542", "y": "796"}, {"x": "553", "y": "796"}, {"x": "553", "y": "786"}]}, "languages": [{"languageCode": "en", "confidence": 0.8818770647}], "text": "42", "confidence": 0.8818770647, "entityIndex": "-1"}], "confidence": 0.8818770647}]}, {"boundingBox": {"vertices": [{"x": "368", "y": "810"}, {"x": "368", "y": "821"}, {"x": "388", "y": "821"}, {"x": "388", "y": "810"}]}, "lines": [{"boundingBox": {"vertices": [{"x": "368", "y": "810"}, {"x": "368", "y": "821"}, {"x": "388", "y": "821"}, {"x": "388", "y": "810"}]}, "words": [{"boundingBox": {"vertices": [{"x": "368", "y": "809"}, {"x": "368", "y": "822"}, {"x": "388", "y": "822"}, {"x": "388", "y": "809"}]}, "languages": [{"languageCode": "en", "confidence": 0.841299057}], "text": "121", "confidence": 0.841299057, "entityIndex": "-1"}], "confidence": 0.841299057}]}, {"boundingBox": {"vertices": [{"x": "402", "y": "807"}, {"x": "402", "y": "820"}, {"x": "422", "y": "820"}, {"x": "422", "y": "807"}]}, "lines": [{"boundingBox": {"vertices": [{"x": "402", "y": "807"}, {"x": "402", "y": "820"}, {"x": "422", "y": "820"}, {"x": "422", "y": "807"}]}, "words": [{"boundingBox": {"vertices": [{"x": "402", "y": "807"}, {"x": "402", "y": "821"}, {"x": "422", "y": "821"}, {"x": "422", "y": "807"}]}, "languages": [{"languageCode": "en", "confidence": 0.8993913531}], "text": "12k", "confidence": 0.8993913531, "entityIndex": "-1"}], "confidence": 0.8993913531}]}, {"boundingBox": {"vertices": [{"x": "671", "y": "808"}, {"x": "671", "y": "824"}, {"x": "791", "y": "824"}, {"x": "791", "y": "808"}]}, "lines": [{"boundingBox": {"vertices": [{"x": "671", "y": "808"}, {"x": "671", "y": "824"}, {"x": "791", "y": "824"}, {"x": "791", "y": "808"}]}, "words": [{"boundingBox": {"vertices": [{"x": "671", "y": "808"}, {"x": "671", "y": "825"}, {"x": "791", "y": "825"}, {"x": "791", "y": "808"}]}, "languages": [{"languageCode": "en", "confidence": 0.9811586738}], "text": "3120-N524-H7", "confidence": 0.9811586738, "entityIndex": "-1"}], "confidence": 0.9811586738}]}, {"boundingBox": {"vertices": [{"x": "919", "y": "809"}, {"x": "919", "y": "824"}, {"x": "1039", "y": "824"}, {"x": "1039", "y": "809"}]}, "lines": [{"boundingBox": {"vertices": [{"x": "919", "y": "809"}, {"x": "919", "y": "824"}, {"x": "1039", "y": "824"}, {"x": "1039", "y": "809"}]}, "words": [{"boundingBox": {"vertices": [{"x": "919", "y": "808"}, {"x": "919", "y": "825"}, {"x": "1039", "y": "825"}, {"x": "1039", "y": "808"}]}, "languages": [{"languageCode": "en", "confidence": 0.9905589819}], "text": "3120-N554-H7", "confidence": 0.9905589819, "entityIndex": "-1"}], "confidence": 0.9905589819}]}, {"boundingBox": {"vertices": [{"x": "385", "y": "875"}, {"x": "385", "y": "886"}, {"x": "394", "y": "886"}, {"x": "394", "y": "875"}]}, "lines": [{"boundingBox": {"vertices": [{"x": "385", "y": "875"}, {"x": "385", "y": "886"}, {"x": "394", "y": "886"}, {"x": "394", "y": "875"}]}, "words": [{"boundingBox": {"vertices": [{"x": "385", "y": "875"}, {"x": "385", "y": "887"}, {"x": "394", "y": "887"}, {"x": "394", "y": "875"}]}, "languages": [{"languageCode": "en", "confidence": 0.7707172036}], "text": "8", "confidence": 0.7707172036, "entityIndex": "-1"}], "confidence": 0.7707172036}]}, {"boundingBox": {"vertices": [{"x": "441", "y": "865"}, {"x": "441", "y": "897"}, {"x": "483", "y": "897"}, {"x": "483", "y": "865"}]}, "lines": [{"boundingBox": {"vertices": [{"x": "441", "y": "865"}, {"x": "441", "y": "897"}, {"x": "483", "y": "897"}, {"x": "483", "y": "865"}]}, "words": [{"boundingBox": {"vertices": [{"x": "441", "y": "865"}, {"x": "441", "y": "900"}, {"x": "483", "y": "900"}, {"x": "483", "y": "865"}]}, "languages": [{"languageCode": "en", "confidence": 0.8365371823}], "text": "2.", "confidence": 0.8365371823, "entityIndex": "-1"}], "confidence": 0.8365371823}]}, {"boundingBox": {"vertices": [{"x": "259", "y": "928"}, {"x": "259", "y": "940"}, {"x": "342", "y": "940"}, {"x": "342", "y": "928"}]}, "lines": [{"boundingBox": {"vertices": [{"x": "259", "y": "928"}, {"x": "259", "y": "940"}, {"x": "342", "y": "940"}, {"x": "342", "y": "928"}]}, "words": [{"boundingBox": {"vertices": [{"x": "259", "y": "928"}, {"x": "259", "y": "940"}, {"x": "312", "y": "940"}, {"x": "312", "y": "928"}]}, "languages": [{"languageCode": "en", "confidence": 0.8368006945}], "text": "mounting", "confidence": 0.8368006945, "entityIndex": "-1"}, {"boundingBox": {"vertices": [{"x": "317", "y": "928"}, {"x": "317", "y": "940"}, {"x": "342", "y": "940"}, {"x": "342", "y": "928"}]}, "languages": [{"languageCode": "en", "confidence": 0.8368006945}], "text": "area", "confidence": 0.8368006945, "entityIndex": "-1"}], "confidence": 0.8368006945}]}, {"boundingBox": {"vertices": [{"x": "130", "y": "998"}, {"x": "130", "y": "1013"}, {"x": "350", "y": "1013"}, {"x": "350", "y": "998"}]}, "lines": [{"boundingBox": {"vertices": [{"x": "130", "y": "998"}, {"x": "130", "y": "1013"}, {"x": "350", "y": "1013"}, {"x": "350", "y": "998"}]}, "words": [{"boundingBox": {"vertices": [{"x": "130", "y": "998"}, {"x": "130", "y": "1012"}, {"x": "167", "y": "1012"}, {"x": "167", "y": "998"}]}, "languages": [{"languageCode": "en", "confidence": 0.8364346623}], "text": "3120", "confidence": 0.8364346623, "entityIndex": "-1"}, {"boundingBox": {"vertices": [{"x": "174", "y": "998"}, {"x": "174", "y": "1012"}, {"x": "204", "y": "1012"}, {"x": "204", "y": "998"}]}, "languages": [{"languageCode": "en", "confidence": 0.8364346623}], "text": "with", "confidence": 0.8364346623, "entityIndex": "-1"}, {"boundingBox": {"vertices": [{"x": "212", "y": "998"}, {"x": "212", "y": "1012"}, {"x": "268", "y": "1012"}, {"x": "268", "y": "998"}]}, "languages": [{"languageCode": "en", "confidence": 0.8364346623}], "text": "push-in", "confidence": 0.8364346623, "entityIndex": "-1"}, {"boundingBox": {"vertices": [{"x": "275", "y": "998"}, {"x": "275", "y": "1013"}, {"x": "350", "y": "1013"}, {"x": "350", "y": "998"}]}, "languages": [{"languageCode": "en", "confidence": 0.8364346623}], "text": "terminals", "confidence": 0.8364346623, "entityIndex": "-1"}], "confidence": 0.8364346623}]}, {"boundingBox": {"vertices": [{"x": "318", "y": "1025"}, {"x": "318", "y": "1056"}, {"x": "513", "y": "1056"}, {"x": "513", "y": "1025"}]}, "lines": [{"boundingBox": {"vertices": [{"x": "320", "y": "1025"}, {"x": "320", "y": "1040"}, {"x": "513", "y": "1040"}, {"x": "513", "y": "1025"}]}, "words": [{"boundingBox": {"vertices": [{"x": "320", "y": "1026"}, {"x": "320", "y": "1039"}, {"x": "350", "y": "1039"}, {"x": "350", "y": "1026"}]}, "languages": [{"languageCode": "en", "confidence": 0.9622828364}], "text": "When", "confidence": 0.9622828364, "entityIndex": "-1"}, {"boundingBox": {"vertices": [{"x": "356", "y": "1027"}, {"x": "356", "y": "1039"}, {"x": "406", "y": "1039"}, {"x": "406", "y": "1027"}]}, "languages": [{"languageCode": "en", "confidence": 0.9622828364}], "text": "Installing", "confidence": 0.9622828364, "entityIndex": "-1"}, {"boundingBox": {"vertices": [{"x": "412", "y": "1027"}, {"x": "412", "y": "1039"}, {"x": "431", "y": "1039"}, {"x": "431", "y": "1027"}]}, "languages": [{"languageCode": "en", "confidence": 0.9622828364}], "text": "the", "confidence": 0.9622828364, "entityIndex": "-1"}, {"boundingBox": {"vertices": [{"x": "464", "y": "1027"}, {"x": "464", "y": "1039"}, {"x": "513", "y": "1039"}, {"x": "513", "y": "1027"}]}, "languages": [{"languageCode": "en", "confidence": 0.9622828364}], "text": "breaker", "confidence": 0.9622828364, "entityIndex": "-1"}], "confidence": 0.9622828364}, {"boundingBox": {"vertices": [{"x": "318", "y": "1042"}, {"x": "318", "y": "1056"}, {"x": "487", "y": "1056"}, {"x": "487", "y": "1042"}]}, "words": [{"boundingBox": {"vertices": [{"x": "318", "y": "1043"}, {"x": "318", "y": "1055"}, {"x": "353", "y": "1055"}, {"x": "353", "y": "1043"}]}, "languages": [{"languageCode": "en", "confidence": 0.9851667285}], "text": "apply", "confidence": 0.9851667285, "entityIndex": "-1"}, {"boundingBox": {"vertices": [{"x": "404", "y": "1042"}, {"x": "404", "y": "1053"}, {"x": "418", "y": "1053"}, {"x": "418", "y": "1042"}]}, "languages": [{"languageCode": "en", "confidence": 0.9851667285}], "text": "on", "confidence": 0.9851667285, "entityIndex": "-1"}, {"boundingBox": {"vertices": [{"x": "425", "y": "1042"}, {"x": "425", "y": "1054"}, {"x": "455", "y": "1054"}, {"x": "455", "y": "1042"}]}, "languages": [{"languageCode": "en", "confidence": 0.9851667285}], "text": "bezel", "confidence": 0.9851667285, "entityIndex": "-1"}, {"boundingBox": {"vertices": [{"x": "458", "y": "1043"}, {"x": "458", "y": "1055"}, {"x": "487", "y": "1055"}, {"x": "487", "y": "1043"}]}, "languages": [{"languageCode": "en", "confidence": 0.9851667285}], "text": "only.", "confidence": 0.9851667285, "entityIndex": "-1"}], "confidence": 0.9851667285}]}, {"boundingBox": {"vertices": [{"x": "297", "y": "1079"}, {"x": "297", "y": "1092"}, {"x": "323", "y": "1092"}, {"x": "323", "y": "1079"}]}, "lines": [{"boundingBox": {"vertices": [{"x": "297", "y": "1079"}, {"x": "297", "y": "1092"}, {"x": "323", "y": "1092"}, {"x": "323", "y": "1079"}]}, "words": [{"boundingBox": {"vertices": [{"x": "297", "y": "1078"}, {"x": "297", "y": "1091"}, {"x": "323", "y": "1091"}, {"x": "323", "y": "1078"}]}, "languages": [{"languageCode": "en", "confidence": 0.9342907667}], "text": "area", "confidence": 0.9342907667, "entityIndex": "-1"}], "confidence": 0.9342907667}]}, {"boundingBox": {"vertices": [{"x": "673", "y": "1082"}, {"x": "673", "y": "1098"}, {"x": "789", "y": "1098"}, {"x": "789", "y": "1082"}]}, "lines": [{"boundingBox": {"vertices": [{"x": "673", "y": "1082"}, {"x": "673", "y": "1098"}, {"x": "789", "y": "1098"}, {"x": "789", "y": "1082"}]}, "words": [{"boundingBox": {"vertices": [{"x": "673", "y": "1082"}, {"x": "673", "y": "1098"}, {"x": "789", "y": "1098"}, {"x": "789", "y": "1082"}]}, "languages": [{"languageCode": "en", "confidence": 0.9110420346}], "text": "3120-N524-N7", "confidence": 0.9110420346, "entityIndex": "-1"}], "confidence": 0.9110420346}]}, {"boundingBox": {"vertices": [{"x": "922", "y": "1082"}, {"x": "922", "y": "1098"}, {"x": "1036", "y": "1098"}, {"x": "1036", "y": "1082"}]}, "lines": [{"boundingBox": {"vertices": [{"x": "922", "y": "1082"}, {"x": "922", "y": "1098"}, {"x": "1036", "y": "1098"}, {"x": "1036", "y": "1082"}]}, "words": [{"boundingBox": {"vertices": [{"x": "922", "y": "1082"}, {"x": "922", "y": "1098"}, {"x": "1036", "y": "1098"}, {"x": "1036", "y": "1082"}]}, "languages": [{"languageCode": "en", "confidence": 0.9204946756}], "text": "3120-N554-N7", "confidence": 0.9204946756, "entityIndex": "-1"}], "confidence": 0.9204946756}]}, {"boundingBox": {"vertices": [{"x": "368", "y": "1223"}, {"x": "368", "y": "1233"}, {"x": "383", "y": "1233"}, {"x": "383", "y": "1223"}]}, "lines": [{"boundingBox": {"vertices": [{"x": "368", "y": "1223"}, {"x": "368", "y": "1233"}, {"x": "383", "y": "1233"}, {"x": "383", "y": "1223"}]}, "words": [{"boundingBox": {"vertices": [{"x": "368", "y": "1222"}, {"x": "368", "y": "1234"}, {"x": "383", "y": "1234"}, {"x": "383", "y": "1222"}]}, "languages": [{"languageCode": "en", "confidence": 0.8838815689}], "text": "121", "confidence": 0.8838815689, "entityIndex": "-1"}], "confidence": 0.8838815689}]}, {"boundingBox": {"vertices": [{"x": "381", "y": "1287"}, {"x": "381", "y": "1303"}, {"x": "396", "y": "1303"}, {"x": "396", "y": "1287"}]}, "lines": [{"boundingBox": {"vertices": [{"x": "381", "y": "1287"}, {"x": "381", "y": "1303"}, {"x": "396", "y": "1303"}, {"x": "396", "y": "1287"}]}, "words": [{"boundingBox": {"vertices": [{"x": "381", "y": "1285"}, {"x": "381", "y": "1305"}, {"x": "396", "y": "1305"}, {"x": "396", "y": "1285"}]}, "languages": [{"languageCode": "en", "confidence": 0.712171793}], "text": "8", "confidence": 0.712171793, "entityIndex": "-1"}], "confidence": 0.712171793}]}, {"boundingBox": {"vertices": [{"x": "466", "y": "1285"}, {"x": "466", "y": "1294"}, {"x": "475", "y": "1294"}, {"x": "475", "y": "1285"}]}, "lines": [{"boundingBox": {"vertices": [{"x": "466", "y": "1285"}, {"x": "466", "y": "1294"}, {"x": "475", "y": "1294"}, {"x": "475", "y": "1285"}]}, "words": [{"boundingBox": {"vertices": [{"x": "466", "y": "1284"}, {"x": "466", "y": "1296"}, {"x": "475", "y": "1296"}, {"x": "475", "y": "1284"}]}, "languages": [{"languageCode": "en", "confidence": 0.711245656}], "text": "7", "confidence": 0.711245656, "entityIndex": "-1"}], "confidence": 0.711245656}]}, {"boundingBox": {"vertices": [{"x": "262", "y": "1338"}, {"x": "262", "y": "1350"}, {"x": "341", "y": "1350"}, {"x": "341", "y": "1338"}]}, "lines": [{"boundingBox": {"vertices": [{"x": "262", "y": "1338"}, {"x": "262", "y": "1350"}, {"x": "341", "y": "1350"}, {"x": "341", "y": "1338"}]}, "words": [{"boundingBox": {"vertices": [{"x": "262", "y": "1339"}, {"x": "262", "y": "1349"}, {"x": "313", "y": "1349"}, {"x": "313", "y": "1339"}]}, "languages": [{"languageCode": "en", "confidence": 0.9389559627}], "text": "mounting", "confidence": 0.9389559627, "entityIndex": "-1"}, {"boundingBox": {"vertices": [{"x": "319", "y": "1339"}, {"x": "319", "y": "1349"}, {"x": "341", "y": "1349"}, {"x": "341", "y": "1339"}]}, "languages": [{"languageCode": "en", "confidence": 0.9389559627}], "text": "area", "confidence": 0.9389559627, "entityIndex": "-1"}], "confidence": 0.9389559627}]}, {"boundingBox": {"vertices": [{"x": "672", "y": "1360"}, {"x": "672", "y": "1377"}, {"x": "788", "y": "1377"}, {"x": "788", "y": "1360"}]}, "lines": [{"boundingBox": {"vertices": [{"x": "672", "y": "1360"}, {"x": "672", "y": "1377"}, {"x": "788", "y": "1377"}, {"x": "788", "y": "1360"}]}, "words": [{"boundingBox": {"vertices": [{"x": "672", "y": "1361"}, {"x": "672", "y": "1377"}, {"x": "788", "y": "1377"}, {"x": "788", "y": "1361"}]}, "languages": [{"languageCode": "en", "confidence": 0.9769518971}], "text": "3120-N524-G7", "confidence": 0.9769518971, "entityIndex": "-1"}], "confidence": 0.9769518971}]}, {"boundingBox": {"vertices": [{"x": "918", "y": "1360"}, {"x": "918", "y": "1378"}, {"x": "1038", "y": "1378"}, {"x": "1038", "y": "1360"}]}, "lines": [{"boundingBox": {"vertices": [{"x": "918", "y": "1360"}, {"x": "918", "y": "1378"}, {"x": "1038", "y": "1378"}, {"x": "1038", "y": "1360"}]}, "words": [{"boundingBox": {"vertices": [{"x": "918", "y": "1360"}, {"x": "918", "y": "1377"}, {"x": "1038", "y": "1377"}, {"x": "1038", "y": "1360"}]}, "languages": [{"languageCode": "en", "confidence": 0.9432498813}], "text": "3120-N554-G7", "confidence": 0.9432498813, "entityIndex": "-1"}], "confidence": 0.9432498813}]}, {"boundingBox": {"vertices": [{"x": "556", "y": "1699"}, {"x": "556", "y": "1714"}, {"x": "661", "y": "1714"}, {"x": "661", "y": "1699"}]}, "lines": [{"boundingBox": {"vertices": [{"x": "556", "y": "1699"}, {"x": "556", "y": "1714"}, {"x": "661", "y": "1714"}, {"x": "661", "y": "1699"}]}, "words": [{"boundingBox": {"vertices": [{"x": "556", "y": "1702"}, {"x": "556", "y": "1713"}, {"x": "598", "y": "1713"}, {"x": "598", "y": "1702"}]}, "languages": [{"languageCode": "en", "confidence": 0.9390432835}], "text": "www.", "confidence": 0.9390432835, "entityIndex": "-1"}, {"boundingBox": {"vertices": [{"x": "603", "y": "1701"}, {"x": "603", "y": "1714"}, {"x": "661", "y": "1714"}, {"x": "661", "y": "1701"}]}, "languages": [{"languageCode": "en", "confidence": 0.9390432835}], "text": "e-t-a.de", "confidence": 0.9390432835}], "confidence": 0.9390432835}]}, {"boundingBox": {"vertices": [{"x": "1100", "y": "1697"}, {"x": "1100", "y": "1714"}, {"x": "1138", "y": "1714"}, {"x": "1138", "y": "1697"}]}, "lines": [{"boundingBox": {"vertices": [{"x": "1100", "y": "1697"}, {"x": "1100", "y": "1714"}, {"x": "1138", "y": "1714"}, {"x": "1138", "y": "1697"}]}, "words": [{"boundingBox": {"vertices": [{"x": "1100", "y": "1698"}, {"x": "1100", "y": "1714"}, {"x": "1138", "y": "1714"}, {"x": "1138", "y": "1698"}]}, "languages": [{"languageCode": "en", "confidence": 0.8720185757}], "text": "1846", "confidence": 0.8720185757, "entityIndex": "-1"}], "confidence": 0.8720185757}]}], "entities": [{"name": "url", "text": "e-t-a.de"}], "width": "1240", "height": "1754"}]}}]}]}