{"results": [{"results": [{"textDetection": {"pages": [{"blocks": [{"boundingBox": {"vertices": [{"x": "78", "y": "87"}, {"x": "78", "y": "117"}, {"x": "427", "y": "117"}, {"x": "427", "y": "87"}]}, "lines": [{"boundingBox": {"vertices": [{"x": "78", "y": "87"}, {"x": "78", "y": "117"}, {"x": "427", "y": "117"}, {"x": "427", "y": "87"}]}, "words": [{"boundingBox": {"vertices": [{"x": "78", "y": "88"}, {"x": "78", "y": "116"}, {"x": "210", "y": "116"}, {"x": "210", "y": "88"}]}, "languages": [{"languageCode": "lt", "confidence": 0.8864721656}], "text": "Mouser", "confidence": 0.8864721656, "entityIndex": "-1"}, {"boundingBox": {"vertices": [{"x": "225", "y": "88"}, {"x": "225", "y": "116"}, {"x": "427", "y": "116"}, {"x": "427", "y": "88"}]}, "languages": [{"languageCode": "lt", "confidence": 0.8864721656}], "text": "Electronics", "confidence": 0.8864721656, "entityIndex": "-1"}], "confidence": 0.8864721656}]}, {"boundingBox": {"vertices": [{"x": "75", "y": "169"}, {"x": "75", "y": "189"}, {"x": "319", "y": "189"}, {"x": "319", "y": "169"}]}, "lines": [{"boundingBox": {"vertices": [{"x": "75", "y": "169"}, {"x": "75", "y": "189"}, {"x": "319", "y": "189"}, {"x": "319", "y": "169"}]}, "words": [{"boundingBox": {"vertices": [{"x": "75", "y": "169"}, {"x": "75", "y": "190"}, {"x": "195", "y": "190"}, {"x": "195", "y": "169"}]}, "languages": [{"languageCode": "en", "confidence": 0.9365279078}], "text": "Authorized", "confidence": 0.9365279078, "entityIndex": "-1"}, {"boundingBox": {"vertices": [{"x": "206", "y": "169"}, {"x": "206", "y": "190"}, {"x": "319", "y": "190"}, {"x": "319", "y": "169"}]}, "languages": [{"languageCode": "en", "confidence": 0.9365279078}], "text": "Distributor", "confidence": 0.9365279078, "entityIndex": "-1"}], "confidence": 0.9365279078}]}, {"boundingBox": {"vertices": [{"x": "76", "y": "269"}, {"x": "76", "y": "298"}, {"x": "915", "y": "298"}, {"x": "915", "y": "269"}]}, "lines": [{"boundingBox": {"vertices": [{"x": "76", "y": "269"}, {"x": "76", "y": "298"}, {"x": "915", "y": "298"}, {"x": "915", "y": "269"}]}, "words": [{"boundingBox": {"vertices": [{"x": "76", "y": "270"}, {"x": "76", "y": "295"}, {"x": "138", "y": "295"}, {"x": "138", "y": "270"}]}, "languages": [{"languageCode": "da", "confidence": 0.9565739632}], "text": "Click", "confidence": 0.9565739632, "entityIndex": "-1"}, {"boundingBox": {"vertices": [{"x": "148", "y": "271"}, {"x": "148", "y": "294"}, {"x": "171", "y": "294"}, {"x": "171", "y": "271"}]}, "languages": [{"languageCode": "da", "confidence": 0.9565739632}], "text": "to", "confidence": 0.9565739632, "entityIndex": "-1"}, {"boundingBox": {"vertices": [{"x": "183", "y": "271"}, {"x": "183", "y": "295"}, {"x": "241", "y": "295"}, {"x": "241", "y": "271"}]}, "languages": [{"languageCode": "da", "confidence": 0.9565739632}], "text": "View", "confidence": 0.9565739632, "entityIndex": "-1"}, {"boundingBox": {"vertices": [{"x": "253", "y": "271"}, {"x": "253", "y": "294"}, {"x": "349", "y": "294"}, {"x": "349", "y": "271"}]}, "languages": [{"languageCode": "da", "confidence": 0.9565739632}], "text": "Pricing,", "confidence": 0.9565739632, "entityIndex": "-1"}, {"boundingBox": {"vertices": [{"x": "358", "y": "270"}, {"x": "358", "y": "295"}, {"x": "486", "y": "295"}, {"x": "486", "y": "270"}]}, "languages": [{"languageCode": "da", "confidence": 0.9565739632}], "text": "Inventory,", "confidence": 0.9565739632, "entityIndex": "-1"}, {"boundingBox": {"vertices": [{"x": "495", "y": "270"}, {"x": "495", "y": "295"}, {"x": "597", "y": "295"}, {"x": "597", "y": "270"}]}, "languages": [{"languageCode": "da", "confidence": 0.9565739632}], "text": "Delivery", "confidence": 0.9565739632, "entityIndex": "-1"}, {"boundingBox": {"vertices": [{"x": "608", "y": "270"}, {"x": "608", "y": "296"}, {"x": "621", "y": "296"}, {"x": "621", "y": "270"}]}, "languages": [{"languageCode": "da", "confidence": 0.9565739632}], "text": "&", "confidence": 0.9565739632, "entityIndex": "-1"}, {"boundingBox": {"vertices": [{"x": "634", "y": "270"}, {"x": "634", "y": "296"}, {"x": "745", "y": "296"}, {"x": "745", "y": "270"}]}, "languages": [{"languageCode": "da", "confidence": 0.9565739632}], "text": "Lifecycle", "confidence": 0.9565739632, "entityIndex": "-1"}, {"boundingBox": {"vertices": [{"x": "756", "y": "270"}, {"x": "756", "y": "296"}, {"x": "915", "y": "296"}, {"x": "915", "y": "270"}]}, "languages": [{"languageCode": "da", "confidence": 0.9565739632}], "text": "Information:", "confidence": 0.9565739632, "entityIndex": "-1"}], "confidence": 0.9565739632}]}, {"boundingBox": {"vertices": [{"x": "69", "y": "404"}, {"x": "69", "y": "507"}, {"x": "998", "y": "507"}, {"x": "998", "y": "404"}]}, "lines": [{"boundingBox": {"vertices": [{"x": "73", "y": "404"}, {"x": "73", "y": "437"}, {"x": "171", "y": "437"}, {"x": "171", "y": "404"}]}, "words": [{"boundingBox": {"vertices": [{"x": "73", "y": "403"}, {"x": "73", "y": "436"}, {"x": "171", "y": "436"}, {"x": "171", "y": "403"}]}, "languages": [{"languageCode": "en", "confidence": 0.9685533047}], "text": "Apem:", "confidence": 0.9685533047, "entityIndex": "-1"}], "confidence": 0.9685533047}, {"boundingBox": {"vertices": [{"x": "87", "y": "444"}, {"x": "87", "y": "471"}, {"x": "998", "y": "471"}, {"x": "998", "y": "444"}]}, "words": [{"boundingBox": {"vertices": [{"x": "87", "y": "443"}, {"x": "87", "y": "469"}, {"x": "305", "y": "469"}, {"x": "305", "y": "443"}]}, "languages": [{"languageCode": "en", "confidence": 0.9072887897}], "text": "Q14F5CZZRGB12ECA", "confidence": 0.9072887897, "entityIndex": "-1"}, {"boundingBox": {"vertices": [{"x": "317", "y": "443"}, {"x": "317", "y": "469"}, {"x": "533", "y": "469"}, {"x": "533", "y": "443"}]}, "languages": [{"languageCode": "en", "confidence": 0.9072887897}], "text": "Q14F5BZZRGB24ECA", "confidence": 0.9072887897, "entityIndex": "-1"}, {"boundingBox": {"vertices": [{"x": "547", "y": "443"}, {"x": "547", "y": "469"}, {"x": "769", "y": "469"}, {"x": "769", "y": "443"}]}, "languages": [{"languageCode": "en", "confidence": 0.9072887897}], "text": "Q14P5CZZRGB12ECA", "confidence": 0.9072887897, "entityIndex": "-1"}, {"boundingBox": {"vertices": [{"x": "782", "y": "443"}, {"x": "782", "y": "469"}, {"x": "998", "y": "469"}, {"x": "998", "y": "443"}]}, "languages": [{"languageCode": "en", "confidence": 0.9072887897}], "text": "Q14F5CZZRGB24ECA", "confidence": 0.9072887897, "entityIndex": "-1"}], "confidence": 0.9072887897}, {"boundingBox": {"vertices": [{"x": "69", "y": "480"}, {"x": "69", "y": "507"}, {"x": "745", "y": "507"}, {"x": "745", "y": "480"}]}, "words": [{"boundingBox": {"vertices": [{"x": "69", "y": "480"}, {"x": "69", "y": "505"}, {"x": "290", "y": "505"}, {"x": "290", "y": "480"}]}, "languages": [{"languageCode": "en", "confidence": 0.8907377124}], "text": "Q14F5BZZRGB12ECA", "confidence": 0.8907377124, "entityIndex": "-1"}, {"boundingBox": {"vertices": [{"x": "306", "y": "481"}, {"x": "306", "y": "505"}, {"x": "521", "y": "505"}, {"x": "521", "y": "481"}]}, "languages": [{"languageCode": "en", "confidence": 0.8907377124}], "text": "Q14P5BZZRGB24ECA", "confidence": 0.8907377124, "entityIndex": "-1"}, {"boundingBox": {"vertices": [{"x": "532", "y": "480"}, {"x": "532", "y": "504"}, {"x": "745", "y": "504"}, {"x": "745", "y": "480"}]}, "languages": [{"languageCode": "en", "confidence": 0.8907377124}], "text": "Q14P5BZZRGB12ECA", "confidence": 0.8907377124, "entityIndex": "-1"}], "confidence": 0.8907377124}]}], "width": "1275", "height": "1650"}]}}]}]}